ceonmedia/__init__.py
ceonmedia/ceonmedia_submission.py
ceonmedia/ceonstock_project_test.json
ceonmedia/config.py
ceonmedia/constants.py
ceonmedia/errors.py
ceonmedia/json_io_example.py
ceonmedia/py.typed
ceonmedia/version.py
ceonmedia/__json_io/__init__.py
ceonmedia/__json_io/submission_input.py
ceonmedia/_json_io/__init__.py
ceonmedia/_json_io/_exporter.py
ceonmedia/_json_io/_file_handler.py
ceonmedia/_json_io/_file_loader.py
ceonmedia/_json_io/_importer.py
ceonmedia/_json_io/cstock_decoder.py
ceonmedia/_json_io/cstock_encoder.py
ceonmedia/_json_io/errors.py
ceonmedia/_json_io/exporter.py
ceonmedia/_json_io/importer.py
ceonmedia/_render_server/_render_app.py
ceonmedia/_render_server/_render_settings.py
ceonmedia/_render_server/_render_task.py
ceonmedia/_software_integrations/__init__.py
ceonmedia/_software_integrations/houdini/__init__.py
ceonmedia/_software_integrations/houdini/_hda_parm_maker.py
ceonmedia/_software_integrations/houdini/_hda_ui_manager.py
ceonmedia/_software_integrations/houdini/_old_setup.zip
ceonmedia/_software_integrations/houdini/hda_ui_manager.py
ceonmedia/_software_integrations/houdini/setup_houdini_env.sh
ceonmedia/_software_integrations/houdini/parm_maker/__init__.py
ceonmedia/_software_integrations/houdini/parm_maker/color.py
ceonmedia/_software_integrations/houdini/parm_maker/create.py
ceonmedia/_software_integrations/houdini/parm_maker/hparms.py
ceonmedia/_software_integrations/houdini/parm_maker/job_inputs.py
ceonmedia/_software_integrations/houdini/parm_maker/parm_types.py
ceonmedia/_submission_server/_actions.py
ceonmedia/_submission_server/_submission.py
ceonmedia/core/README.md
ceonmedia/core/__init__.py
ceonmedia/core/_render_task.py
ceonmedia/core/base.py
ceonmedia/core/file_action.py
ceonmedia/core/file_reference.py
ceonmedia/core/job.py
ceonmedia/core/job_input.py
ceonmedia/core/loader.py
ceonmedia/core/project.py
ceonmedia/core/project_input.py
ceonmedia/core/render.py
ceonmedia/core/submission_input.py
ceonmedia-0.3.3.dist-info/METADATA
ceonmedia-0.3.3.dist-info/WHEEL
ceonmedia-0.3.3.dist-info/RECORD
