Metadata-Version: 2.4
Name: ceonmedia
Version: 0.3.3
Summary: Core functionality for ceonmedia projects
Author-email: Dayne Kolk <daynekolk@hotmail.com>
Requires-Python: >=3.11
Requires-Dist: ceon-render>=0.2.1
